<Properties StartupConfiguration="{3217702B-D977-441B-A748-10DCCF9922AC}|">
  <MonoDevelop.Ide.Workbench ActiveDocument="Controllers/RecipeController.cs">
    <Files>
      <File FileName="Scripts/Display.js" Line="106" Column="5" />
      <File FileName="Content/RecipePage.css" Line="25" Column="24" />
      <File FileName="Views/Recipe/_Tools.cshtml" Line="2" Column="58" />
      <File FileName="Content/Tools.css" Line="1" Column="17" />
      <File FileName="Content/HomePage.css" Line="1" Column="1" />
      <File FileName="Views/Recipe/_Ingredients.cshtml" Line="10" Column="8" />
      <File FileName="Views/Recipe/Display.cshtml" Line="37" Column="18" />
      <File FileName="Content/Ingredients.css" Line="6" Column="1" />
      <File FileName="Controllers/RecipeController.cs" Line="34" Column="43" />
    </Files>
  </MonoDevelop.Ide.Workbench>
  <MonoDevelop.Ide.Workspace ActiveConfiguration="Debug" />
  <MonoDevelop.Ide.DebuggingService.Breakpoints>
    <BreakpointStore>
      <Breakpoint file="/Users/wilkin/Projects/Coding_Projects/LLFRecipes/Recipes/Controllers/RecipeController.cs" relfile="Controllers/RecipeController.cs" line="35" column="1" />
    </BreakpointStore>
  </MonoDevelop.Ide.DebuggingService.Breakpoints>
  <MonoDevelop.Ide.DebuggingService.PinnedWatches />
  <MultiItemStartupConfigurations />
  <MonoDevelop.Ide.ItemProperties.Recipes PreferredExecutionTarget="MonoDevelop.Default" />
</Properties>